acronym_extraction/__init__.py
acronym_extraction/extract_acronyms.py
acronym_extraction/preprocessing.py
acronym_extractor-2.0.7.dist-info/METADATA
acronym_extractor-2.0.7.dist-info/WHEEL
acronym_extractor-2.0.7.dist-info/entry_points.txt
acronym_extractor-2.0.7.dist-info/top_level.txt
acronym_extractor-2.0.7.dist-info/RECORD
