Metadata-Version: 2.1
Name: acronym-extractor
Version: 2.0.7
Summary: Extracting acronym-definition pairs from pdf or text files
Home-page: https://github.com/ali-izhar/acronym_extraction
Author: Izhar Ali
Author-email: <izharali.skt@gmail.com>
Keywords: python,java,acronyms,extraction,text analysis,pdf to text
Classifier: Development Status :: 5 - Production/Stable
Classifier: Intended Audience :: Developers
Classifier: Programming Language :: Python :: 3
Classifier: Operating System :: Microsoft :: Windows
Requires-Python: >=3.6
Requires-Dist: nltk
Requires-Dist: tika
Requires-Dist: beautifulsoup4
Requires-Dist: lxml
